CHANGES.txt
MANIFEST.in
README.rst
docs_requirements.txt
setup.py
tests_requirements.txt
docs/_build/html/_sources/index.txt
docs/_build/html/_sources/state_machine.txt
docs/_build/html/_sources/state_machine_db.txt
state_machine_db/__init__.py
state_machine_db/state_machine.py
state_machine_db.egg-info/PKG-INFO
state_machine_db.egg-info/SOURCES.txt
state_machine_db.egg-info/dependency_links.txt
state_machine_db.egg-info/top_level.txt