Metadata-Version: 1.1
Name: state-machine-db
Version: 0.1
Summary: Provides the implementation of a configurable state machine
Home-page: https://github.com/jonDel/state_machine_db
Author: Jonatan Dellagostin
Author-email: jdellagostin@gmail.com
License: GPLv3
Keywords: state machine finite
Platform: UNKNOWN
Classifier: Development Status :: 3 - Alpha
Classifier: License :: OSI Approved :: GNU General Public License v3 (GPLv3)
Classifier: Programming Language :: Python :: 2.6
Classifier: Programming Language :: Python :: 2.7
Classifier: Topic :: System :: Shells
